<freeStyleBuild><action><parameter><name>REPO</name><value>OSS/com.ericsson.oss.pmic/pm-service</value></parameter></action><action><cause><shortDescription>Started by user Diarmuid Healy</shortDescription><userId>ezheadi</userId><userName>Diarmuid Healy</userName></cause></action><action></action><action></action><action><buildsByBranchName><gcmmaster><buildNumber>850</buildNumber><marked><SHA1>5d26b82277640a482fa4f565ca47955ad8e8119b</SHA1><branch><SHA1>5d26b82277640a482fa4f565ca47955ad8e8119b</SHA1><name>gcm/master</name></branch></marked><revision><SHA1>5d26b82277640a482fa4f565ca47955ad8e8119b</SHA1><branch><SHA1>5d26b82277640a482fa4f565ca47955ad8e8119b</SHA1><name>gcm/master</name></branch></revision></gcmmaster><gcnmaster><buildNumber>434</buildNumber><marked><SHA1>444ca2f49b61672b50c8ec9a5b4d8e1276bdb95c</SHA1><branch><SHA1>444ca2f49b61672b50c8ec9a5b4d8e1276bdb95c</SHA1><name>gcn/master</name></branch></marked><revision><SHA1>444ca2f49b61672b50c8ec9a5b4d8e1276bdb95c</SHA1><branch><SHA1>444ca2f49b61672b50c8ec9a5b4d8e1276bdb95c</SHA1><name>gcn/master</name></branch></revision></gcnmaster></buildsByBranchName><lastBuiltRevision><SHA1>5d26b82277640a482fa4f565ca47955ad8e8119b</SHA1><branch><SHA1>5d26b82277640a482fa4f565ca47955ad8e8119b</SHA1><name>gcm/master</name></branch></lastBuiltRevision><remoteUrl>${GERRIT_CENTRAL}/${REPO}</remoteUrl><remoteUrl>${GERRIT_MIRROR}/${REPO}</remoteUrl><scmName></scmName></action><action></action><action></action><action></action><action></action><action></action><action></action><building>true</building><displayName>#850 - OSS/com.ericsson.oss.pmic/pm-service by </displayName><duration>0</duration><estimatedDuration>25050</estimatedDuration><executor></executor><fullDisplayName>Admin_Sprint_Version_Update #850 - OSS/com.ericsson.oss.pmic/pm-service by </fullDisplayName><id>850</id><keepLog>false</keepLog><number>850</number><queueId>234188</queueId><timestamp>1578558139623</timestamp><url>https://fem126-eiffel004.lmera.ericsson.se:8443/jenkins/job/Admin_Sprint_Version_Update/850/</url><builtOn></builtOn><changeSet><kind>git</kind></changeSet></freeStyleBuild>